eikon/Profile.py
eikon/__init__.py
eikon/data_grid.py
eikon/eikonError.py
eikon/json_requests.py
eikon/news_request.py
eikon/symbology.py
eikon/time_series.py
eikon/tools.py
eikon/streaming_session/__init__.py
eikon/streaming_session/cache.py
eikon/streaming_session/desktop_session.py
eikon/streaming_session/istream_callback.py
eikon/streaming_session/itemstream.py
eikon/streaming_session/session.py
eikon/streaming_session/stream.py
eikon/streaming_session/stream_connection.py
eikon/streaming_session/streaming_connection_config.py
eikon/streaming_session/streamingprice.py
eikon/streaming_session/streamingprice_callback.py
eikon/streaming_session/streamingprices.py
eikon_docker-0.0.1.dist-info/LICENSE.txt
eikon_docker-0.0.1.dist-info/METADATA
eikon_docker-0.0.1.dist-info/WHEEL
eikon_docker-0.0.1.dist-info/top_level.txt
eikon_docker-0.0.1.dist-info/RECORD
