Metadata-Version: 2.1
Name: eikon-docker
Version: 0.0.1
Summary: Use the Python Eikon Data API from within a container
Home-page: https://github.com/tschm/eikon-docker
Author: Thomas Schmelzer
Author-email: thomas.schmelzer@gmail.com
License: Apache 2.0
Platform: UNKNOWN
Requires-Dist: requests (==2.22.0)
Requires-Dist: appdirs (==1.4.3)
Requires-Dist: requests-async (==0.6.2)
Requires-Dist: websocket-client
Requires-Dist: deprecation
Requires-Dist: nest-asyncio (==1.0.0)
Requires-Dist: pandas
